pohualli/__init__.py
pohualli/__main__.py
pohualli/autocorr.py
pohualli/aztec.py
pohualli/calendar_dates.py
pohualli/cli.py
pohualli/composite.py
pohualli/correlations.py
pohualli/cycle819.py
pohualli/desktop_app.py
pohualli/maya.py
pohualli/moon.py
pohualli/planets.py
pohualli/types.py
pohualli/webapp.py
pohualli/yearbear.py
pohualli/zodiac.py
pohualli/templates/index.html
pohualli-0.3.1.dist-info/licenses/LICENSE
pohualli-0.3.1.dist-info/METADATA
pohualli-0.3.1.dist-info/WHEEL
pohualli-0.3.1.dist-info/entry_points.txt
pohualli-0.3.1.dist-info/top_level.txt
pohualli-0.3.1.dist-info/RECORD
