Metadata-Version: 2.4
Name: pohualli
Version: 0.3.1
Summary: Python port (in progress) of the Turbo Pascal Pohualli calendrical utility
Author: Port Maintainers
License: GNU GENERAL PUBLIC LICENSE
Project-URL: Homepage, https://github.com/muscariello/pohualli-python
Project-URL: Documentation, https://muscariello.github.io/pohualli-python/
Project-URL: Source, https://github.com/muscariello/pohualli-python
Project-URL: Issues, https://github.com/muscariello/pohualli-python/issues
Keywords: maya,aztec,calendar,mesoamerican,astronomy,long-count,tzolkin,haab
Classifier: Development Status :: 3 - Alpha
Classifier: Intended Audience :: Science/Research
Classifier: Programming Language :: Python :: 3
Classifier: Programming Language :: Python :: 3.10
Classifier: Programming Language :: Python :: 3.11
Classifier: Programming Language :: Python :: 3.12
Classifier: Programming Language :: Python :: 3.13
Classifier: Topic :: Scientific/Engineering :: Astronomy
Classifier: Topic :: Scientific/Engineering :: Information Analysis
Requires-Python: >=3.10
License-File: LICENSE
Provides-Extra: dev
Requires-Dist: pytest; extra == "dev"
Requires-Dist: pytest-cov; extra == "dev"
Requires-Dist: coverage>=7.6.0; extra == "dev"
Requires-Dist: briefcase>=0.3.20; extra == "dev"
Provides-Extra: web
Requires-Dist: fastapi; extra == "web"
Requires-Dist: uvicorn; extra == "web"
Requires-Dist: jinja2; extra == "web"
Requires-Dist: httpx; extra == "web"
Provides-Extra: docs
Requires-Dist: mkdocs>=1.6.0; extra == "docs"
Requires-Dist: mkdocs-material>=9.5.0; extra == "docs"
Requires-Dist: mkdocs-gen-files; extra == "docs"
Requires-Dist: mkdocs-literate-nav; extra == "docs"
Requires-Dist: mkdocs-section-index; extra == "docs"
Dynamic: license-file
